[
    {
        "name": "DMEGC Infinity 450W",
        "model": "DM450M10RT-B54HBT-L",
        "manufacturer": "DMEGC",
        "panel-series": "",
        "height": 1762,
        "width": 1134,
        "depth": 30,
        "weight": 20.4,
        "glass": "Dual (1.6mm + 1.6mm)",
        "bifacial": true,
        "power": 450,
        "voc": 41.05,
        "vmp": 33.79,
        "isc": 13.91,
        "imp": 13.32,
        "price": 95,
        "efficiency": 22.5,
        "tempCoefPmax": -0.29,
        "tempCoefVoc": -0.25,
        "tempCoefIsc": 0.048,
        "maxSeriesFuse": 25,
        "maxSystemVoltage": 1500,
        "cells": "108 Half-Cell (N-Type)",
        "gseCompatibility": "Both",
        "datasheetUrl": "https://www.dmegcsolar.com/upload/img/2024-08/66b9d7c1aba04.pdf",
        "notes": "A very strong middle-ground option. Offers the durability of double-glass and bifacial cell tech with excellent voltage profiles.",
        "buyLinks": [],
        "active": true,
        "reviewed": false,
        "availableUK": true
    },
    {
        "name": "DMEGC Infinity 455W",
        "model": "DM455M10RT-B54HBT-L",
        "manufacturer": "DMEGC",
        "panel-series": "",
        "height": 1762,
        "width": 1134,
        "depth": 30,
        "weight": 20.4,
        "glass": "Dual (1.6mm + 1.6mm)",
        "bifacial": true,
        "power": 455,
        "voc": 41.25,
        "vmp": 33.99,
        "isc": 13.99,
        "imp": 13.39,
        "price": 98,
        "efficiency": 22.8,
        "tempCoefPmax": -0.29,
        "tempCoefVoc": -0.25,
        "tempCoefIsc": 0.048,
        "maxSeriesFuse": 25,
        "maxSystemVoltage": 1500,
        "cells": "108 Half-Cell (N-Type)",
        "gseCompatibility": "Both",
        "datasheetUrl": "https://www.dmegcsolar.com/upload/img/2024-08/66b9d7c1aba04.pdf",
        "notes": "Solid N-Type bifacial panel. High quality build with premium efficiency ratings.",
        "buyLinks": [],
        "active": true,
        "reviewed": false,
        "availableUK": true
    },
    {
        "name": "DMEGC Infinity 460W",
        "model": "DM460M10RT-B54HBT-L",
        "manufacturer": "DMEGC",
        "panel-series": "",
        "height": 1762,
        "width": 1134,
        "depth": 30,
        "weight": 20.4,
        "glass": "Dual (1.6mm + 1.6mm)",
        "bifacial": true,
        "power": 460,
        "voc": 41.45,
        "vmp": 34.19,
        "isc": 14.07,
        "imp": 13.46,
        "price": 100,
        "efficiency": 23,
        "tempCoefPmax": -0.29,
        "tempCoefVoc": -0.25,
        "tempCoefIsc": 0.048,
        "maxSeriesFuse": 25,
        "maxSystemVoltage": 1500,
        "cells": "108 Half-Cell (N-Type)",
        "gseCompatibility": "Both",
        "datasheetUrl": "https://www.dmegcsolar.com/upload/img/2024-08/66b9d7c1aba04.pdf",
        "notes": "Higher power variant of the Infinity series. Top-tier efficiency for standard-sized modules.",
        "buyLinks": [],
        "active": true,
        "reviewed": false,
        "availableUK": true
    },
    {
        "name": "DMEGC Infinity 465W",
        "model": "DM465M10RT-B54HBT-L",
        "manufacturer": "DMEGC",
        "panel-series": "",
        "height": 1762,
        "width": 1134,
        "depth": 30,
        "weight": 20.4,
        "glass": "Dual (1.6mm + 1.6mm)",
        "bifacial": true,
        "power": 465,
        "voc": 41.65,
        "vmp": 34.39,
        "isc": 14.15,
        "imp": 13.53,
        "price": 105,
        "efficiency": 23.3,
        "tempCoefPmax": -0.29,
        "tempCoefVoc": -0.25,
        "tempCoefIsc": 0.048,
        "maxSeriesFuse": 25,
        "maxSystemVoltage": 1500,
        "cells": "108 Half-Cell (N-Type)",
        "gseCompatibility": "Both",
        "datasheetUrl": "https://www.dmegcsolar.com/upload/img/2024-08/66b9d7c1aba04.pdf",
        "notes": "Premium power bin. Best-in-class performance for residential bifacial applications.",
        "buyLinks": [],
        "active": true,
        "reviewed": false,
        "availableUK": true
    },
    {
        "name": "DMEGC G12 Infinity RT 515W",
        "model": "DM515G12RT-B54HBT",
        "manufacturer": "DMEGC",
        "panel-series": "",
        "height": 1977,
        "width": 1134,
        "depth": 30,
        "weight": 27.1,
        "glass": "Dual (2.0mm + 2.0mm)",
        "bifacial": true,
        "power": 515,
        "voc": 40.75,
        "vmp": 34.61,
        "isc": 15.83,
        "imp": 14.88,
        "price": 92,
        "efficiency": 22.9,
        "tempCoefPmax": -0.29,
        "tempCoefVoc": -0.25,
        "tempCoefIsc": 0.048,
        "maxSeriesFuse": 30,
        "maxSystemVoltage": 1500,
        "cells": "108 Half-Cell (G12 RT)",
        "gseCompatibility": "Portrait Only",
        "datasheetUrl": "https://www.dmegcsolar.com/upload/img/2024-08/66b9d7c1aba04.pdf",
        "notes": "ENGINEERING WARNING: Uses larger G12-RT rectangular wafers. Massive 16A current pushes many MPPTs to their limit. Verify safety margins for cloud-edge effects.",
        "buyLinks": [
            {
                "Supplier": "City Plumbing",
                "URL": "https://www.cityplumbing.co.uk/p/dmegc-515w-all-black-solar-panel/p/223866",
                "isAffiliate": false
            }
        ],
        "active": true,
        "reviewed": true,
        "availableUK": true
    },
    {
        "name": "DMEGC Infinity RT 465W",
        "model": "DM465G12RT-G48HBB",
        "manufacturer": "DMEGC",
        "panel-series": "Infinity RT",
        "height": 1762,
        "width": 1134,
        "depth": 30,
        "weight": 24,
        "glass": "Dual (2.0mm + 2.0mm)",
        "bifacial": false,
        "power": 465,
        "voc": 36.46,
        "vmp": 31.21,
        "isc": 15.88,
        "imp": 14.91,
        "price": 88.42,
        "efficiency": 23.3,
        "tempCoefPmax": -0.29,
        "tempCoefVoc": -0.25,
        "tempCoefIsc": 0.058,
        "maxSeriesFuse": 25,
        "maxSystemVoltage": 1500,
        "cells": "G12 Infinity RT",
        "gseCompatibility": "Both",
        "datasheetUrl": "https://www.cityplumbing.co.uk/p/dmegc-465w-g12-all-black-solar-panel/p/231059",
        "notes": "",
        "buyLinks": [
            {
                "Supplier": "City Plumbing",
                "URL": "https://www.cityplumbing.co.uk/p/dmegc-465w-g12-all-black-solar-panel/p/231059",
                "isAffiliate": false
            }
        ],
        "active": true,
        "reviewed": false,
        "availableUK": true
    }
]